{"assets":[{"id":"image_0","w":148,"h":29,"u":"images/","p":"img_0.png"},{"id":"image_1","w":190,"h":37,"u":"images/","p":"img_1.png"},{"id":"image_2","w":59,"h":29,"u":"images/","p":"img_2.png"},{"id":"image_3","w":533,"h":37,"u":"images/","p":"img_3.png"},{"id":"comp_0","layers":[{"ddd":0,"ind":0,"ty":4,"nm":"形状图层 6","ks":{"o":{"k":100},"r":{"k":0},"p":{"k":[{"i":{"x":0,"y":1},"o":{"x":0.167,"y":0.167},"n":"0_1_0p167_0p167","t":59,"s":[715.75,790,0],"e":[767.75,790,0],"to":[8.66666698455811,0,0],"ti":[-8.66666698455811,0,0]},{"t":61}]},"a":{"k":[0,0,0]},"s":{"k":[100,100,100]}},"ao":0,"shapes":[{"ind":0,"ty":"sh","ks":{"k":{"i":[[-10.931,0],[0,-10.888],[10.931,0],[0,10.888]],"o":[[10.931,0],[0,10.888],[-10.931,0],[0,-10.888]],"v":[[0,-19.714],[19.792,0],[0,19.714],[-19.792,0]],"c":true}},"nm":"路径 1","mn":"ADBE Vector Shape - Group"},{"ty":"fl","fillEnabled":true,"c":{"k":[1,1,1,1]},"o":{"k":100},"nm":"填充 1","mn":"ADBE Vector Graphic - Fill"}],"ip":0,"op":150,"st":0,"bm":0,"sr":1},{"ddd":0,"ind":1,"ty":4,"nm":"形状图层 7","ks":{"o":{"k":[{"i":{"x":[0.833],"y":[0.833]},"o":{"x":[0.167],"y":[0.167]},"n":["0p833_0p833_0p167_0p167"],"t":59,"s":[0],"e":[40]},{"i":{"x":[0.833],"y":[0.833]},"o":{"x":[0.167],"y":[0.167]},"n":["0p833_0p833_0p167_0p167"],"t":67,"s":[40],"e":[0]},{"t":75}]},"r":{"k":0},"p":{"k":[768.25,790,0]},"a":{"k":[0,0,0]},"s":{"k":[{"i":{"x":[0.218,0.218,0.667],"y":[1,1,0.667]},"o":{"x":[0.167,0.167,0.167],"y":[0.167,0.167,0.167]},"n":["0p218_1_0p167_0p167","0p218_1_0p167_0p167","0p667_0p667_0p167_0p167"],"t":59,"s":[100,100,100],"e":[238,238,100]},{"t":68}]}},"ao":0,"shapes":[{"ind":0,"ty":"sh","ks":{"k":{"i":[[-10.931,0],[0,-10.888],[10.931,0],[0,10.888]],"o":[[10.931,0],[0,10.888],[-10.931,0],[0,-10.888]],"v":[[0,-19.714],[19.792,0],[0,19.714],[-19.792,0]],"c":true}},"nm":"路径 1","mn":"ADBE Vector Shape - Group"},{"ty":"fl","fillEnabled":true,"c":{"k":[0.31,0.59,1,1]},"o":{"k":100},"nm":"填充 1","mn":"ADBE Vector Graphic - Fill"}],"ip":0,"op":150,"st":0,"bm":0,"sr":1},{"ddd":0,"ind":2,"ty":4,"nm":"形状图层 5","ks":{"o":{"k":[{"i":{"x":[0.833],"y":[0.833]},"o":{"x":[0.167],"y":[0.167]},"n":["0p833_0p833_0p167_0p167"],"t":60,"s":[100],"e":[0]},{"t":62}]},"r":{"k":0},"p":{"k":[742,790,0]},"a":{"k":[0,0,0]},"s":{"k":[100,100,100]}},"ao":0,"shapes":[{"ind":0,"ty":"sh","ks":{"k":{"i":[[-14.912,0],[0,0],[0,-14.912],[14.912,0],[0,0],[0,14.912]],"o":[[0,0],[14.912,0],[0,14.912],[0,0],[-14.912,0],[0,-14.912]],"v":[[-27,-27],[27,-27],[54,0],[27,27],[-27,27],[-54,0]],"c":true}},"nm":"路径 1","mn":"ADBE Vector Shape - Group"},{"ty":"fl","fillEnabled":true,"c":{"k":[0.59,0.59,0.59,1]},"o":{"k":100},"nm":"填充 1","mn":"ADBE Vector Graphic - Fill"}],"ip":0,"op":150,"st":0,"bm":0,"sr":1},{"ddd":0,"ind":3,"ty":4,"nm":"形状图层 3","ks":{"o":{"k":100},"r":{"k":0},"p":{"k":[742,790,0]},"a":{"k":[0,0,0]},"s":{"k":[100,100,100]}},"ao":0,"shapes":[{"ind":0,"ty":"sh","ks":{"k":{"i":[[-14.912,0],[0,0],[0,-14.912],[14.912,0],[0,0],[0,14.912]],"o":[[0,0],[14.912,0],[0,14.912],[0,0],[-14.912,0],[0,-14.912]],"v":[[-27,-27],[27,-27],[54,0],[27,27],[-27,27],[-54,0]],"c":true}},"nm":"路径 1","mn":"ADBE Vector Shape - Group"},{"ty":"fl","fillEnabled":true,"c":{"k":[0.44,0.67,1,1]},"o":{"k":100},"nm":"填充 1","mn":"ADBE Vector Graphic - Fill"}],"ip":0,"op":150,"st":0,"bm":0,"sr":1},{"ddd":0,"ind":4,"ty":2,"nm":"焕彩来电秀.png","cl":"png","refId":"image_0","ks":{"o":{"k":100},"r":{"k":0},"p":{"k":[348,695.5,0]},"a":{"k":[74,14.5,0]},"s":{"k":[100,100,100]}},"ao":0,"ip":0,"op":150,"st":0,"bm":0,"sr":1},{"ddd":0,"ind":6,"ty":2,"nm":"大焕彩来电秀.png","cl":"png","refId":"image_1","ks":{"o":{"k":100},"r":{"k":0},"p":{"k":[367,787.5,0]},"a":{"k":[95,18.5,0]},"s":{"k":[100,100,100]}},"ao":0,"ip":0,"op":150,"st":0,"bm":0,"sr":1},{"ddd":0,"ind":8,"ty":4,"nm":"形状图层 2","ks":{"o":{"k":100},"r":{"k":0},"p":{"k":[540,788.75,0]},"a":{"k":[0,0,0]},"s":{"k":[100,100,100]}},"ao":0,"shapes":[{"ind":0,"ty":"sh","ks":{"k":{"i":[[0,0],[0,0],[0,0],[0,0]],"o":[[0,0],[0,0],[0,0],[0,0]],"v":[[-300,-54],[300,-54],[300,54],[-300,54]],"c":true}},"nm":"路径 1","mn":"ADBE Vector Shape - Group"},{"ty":"fl","fillEnabled":true,"c":{"k":[1,1,1,1]},"o":{"k":100},"nm":"填充 1","mn":"ADBE Vector Graphic - Fill"}],"ip":0,"op":150,"st":0,"bm":0,"sr":1},{"ddd":0,"ind":9,"ty":4,"nm":"屏幕 4","ks":{"o":{"k":100},"r":{"k":0},"p":{"k":[540,831,0]},"a":{"k":[0,0,0]},"s":{"k":[100,100,100]}},"ao":0,"shapes":[{"ind":0,"ty":"sh","ks":{"k":{"i":[[-3.314,0],[0,0],[0,-3.314],[0,0],[0,0],[0,0]],"o":[[0,0],[3.314,0],[0,0],[0,0],[0,0],[0,-3.314]],"v":[[-294,-175],[294,-175],[300,-169],[300,175],[-300,175],[-300,-169]],"c":true}},"nm":"路径 1","mn":"ADBE Vector Shape - Group"},{"ty":"fl","fillEnabled":true,"c":{"k":[0.97,0.97,0.97,1]},"o":{"k":100},"nm":"填充 1","mn":"ADBE Vector Graphic - Fill"}],"ip":0,"op":150,"st":0,"bm":0,"sr":1}]},{"id":"comp_1","layers":[{"ddd":0,"ind":0,"ty":4,"nm":"形状图层 10","parent":8,"ks":{"o":{"k":100},"r":{"k":0},"p":{"k":[116,164,0]},"a":{"k":[0,0,0]},"s":{"k":[100,100,100]}},"ao":0,"shapes":[{"ind":0,"ty":"sh","ks":{"k":{"i":[[-6.627,0],[0,0],[0,-6.627],[6.627,0],[0,0],[0,6.627]],"o":[[0,0],[6.627,0],[0,6.627],[0,0],[-6.627,0],[0,-6.627]],"v":[[-72,-12],[72,-12],[84,0],[72,12],[-72,12],[-84,0]],"c":true}},"nm":"路径 1","mn":"ADBE Vector Shape - Group"},{"ty":"fl","fillEnabled":true,"c":{"k":[0.95,0.95,0.95,1]},"o":{"k":100},"nm":"填充 1","mn":"ADBE Vector Graphic - Fill"}],"ip":0,"op":150,"st":0,"bm":0,"sr":1},{"ddd":0,"ind":1,"ty":4,"nm":"形状图层 9","parent":8,"ks":{"o":{"k":100},"r":{"k":0},"p":{"k":[116,-54,0]},"a":{"k":[0,0,0]},"s":{"k":[100,100,100]}},"ao":0,"shapes":[{"ind":0,"ty":"sh","ks":{"k":{"i":[[-6.627,0],[0,0],[0,-6.627],[6.627,0],[0,0],[0,6.627]],"o":[[0,0],[6.627,0],[0,6.627],[0,0],[-6.627,0],[0,-6.627]],"v":[[-72,-12],[72,-12],[84,0],[72,12],[-72,12],[-84,0]],"c":true}},"nm":"路径 1","mn":"ADBE Vector Shape - Group"},{"ty":"fl","fillEnabled":true,"c":{"k":[0.95,0.95,0.95,1]},"o":{"k":100},"nm":"填充 1","mn":"ADBE Vector Graphic - Fill"}],"ip":0,"op":150,"st":0,"bm":0,"sr":1},{"ddd":0,"ind":2,"ty":4,"nm":"形状图层 8","parent":8,"ks":{"o":{"k":100},"r":{"k":0},"p":{"k":[116,-166,0]},"a":{"k":[0,0,0]},"s":{"k":[100,100,100]}},"ao":0,"shapes":[{"ind":0,"ty":"sh","ks":{"k":{"i":[[-6.627,0],[0,0],[0,-6.627],[6.627,0],[0,0],[0,6.627]],"o":[[0,0],[6.627,0],[0,6.627],[0,0],[-6.627,0],[0,-6.627]],"v":[[-72,-12],[72,-12],[84,0],[72,12],[-72,12],[-84,0]],"c":true}},"nm":"路径 1","mn":"ADBE Vector Shape - Group"},{"ty":"fl","fillEnabled":true,"c":{"k":[0.95,0.95,0.95,1]},"o":{"k":100},"nm":"填充 1","mn":"ADBE Vector Graphic - Fill"}],"ip":0,"op":150,"st":0,"bm":0,"sr":1},{"ddd":0,"ind":3,"ty":4,"nm":"形状图层 7","parent":8,"ks":{"o":{"k":100},"r":{"k":0},"p":{"k":[116,-276,0]},"a":{"k":[0,0,0]},"s":{"k":[100,100,100]}},"ao":0,"shapes":[{"ind":0,"ty":"sh","ks":{"k":{"i":[[-6.627,0],[0,0],[0,-6.627],[6.627,0],[0,0],[0,6.627]],"o":[[0,0],[6.627,0],[0,6.627],[0,0],[-6.627,0],[0,-6.627]],"v":[[-72,-12],[72,-12],[84,0],[72,12],[-72,12],[-84,0]],"c":true}},"nm":"路径 1","mn":"ADBE Vector Shape - Group"},{"ty":"fl","fillEnabled":true,"c":{"k":[0.95,0.95,0.95,1]},"o":{"k":100},"nm":"填充 1","mn":"ADBE Vector Graphic - Fill"}],"ip":0,"op":150,"st":0,"bm":0,"sr":1},{"ddd":0,"ind":4,"ty":4,"nm":"形状图层 4","parent":8,"ks":{"o":{"k":100},"r":{"k":0},"p":{"k":[300,-56,0]},"a":{"k":[0,0,0]},"s":{"k":[100,100,100]}},"ao":0,"shapes":[{"ind":0,"ty":"sh","ks":{"k":{"i":[[0,0],[0,0],[0,0],[0,0]],"o":[[0,0],[0,0],[0,0],[0,0]],"v":[[-300,-54],[300,-54],[300,54],[-300,54]],"c":true}},"nm":"路径 1","mn":"ADBE Vector Shape - Group"},{"ty":"fl","fillEnabled":true,"c":{"k":[1,1,1,1]},"o":{"k":100},"nm":"填充 1","mn":"ADBE Vector Graphic - Fill"}],"ip":0,"op":150,"st":0,"bm":0,"sr":1},{"ddd":0,"ind":5,"ty":4,"nm":"形状图层 3","parent":8,"ks":{"o":{"k":100},"r":{"k":0},"p":{"k":[300,-166,0]},"a":{"k":[0,0,0]},"s":{"k":[100,100,100]}},"ao":0,"shapes":[{"ind":0,"ty":"sh","ks":{"k":{"i":[[0,0],[0,0],[0,0],[0,0]],"o":[[0,0],[0,0],[0,0],[0,0]],"v":[[-300,-54],[300,-54],[300,54],[-300,54]],"c":true}},"nm":"路径 1","mn":"ADBE Vector Shape - Group"},{"ty":"fl","fillEnabled":true,"c":{"k":[1,1,1,1]},"o":{"k":100},"nm":"填充 1","mn":"ADBE Vector Graphic - Fill"}],"ip":0,"op":150,"st":0,"bm":0,"sr":1},{"ddd":0,"ind":6,"ty":4,"nm":"形状图层 1","parent":8,"ks":{"o":{"k":100},"r":{"k":0},"p":{"k":[300,-276,0]},"a":{"k":[0,0,0]},"s":{"k":[100,100,100]}},"ao":0,"shapes":[{"ind":0,"ty":"sh","ks":{"k":{"i":[[0,0],[0,0],[0,0],[0,0]],"o":[[0,0],[0,0],[0,0],[0,0]],"v":[[-300,-57],[300,-57],[300,54],[-300,54]],"c":true}},"nm":"路径 1","mn":"ADBE Vector Shape - Group"},{"ty":"fl","fillEnabled":true,"c":{"k":[1,1,1,1]},"o":{"k":100},"nm":"填充 1","mn":"ADBE Vector Graphic - Fill"}],"ip":0,"op":150,"st":0,"bm":0,"sr":1},{"ddd":0,"ind":7,"ty":4,"nm":"形状图层 2","parent":8,"ks":{"o":{"k":100},"r":{"k":0},"p":{"k":[300,164,0]},"a":{"k":[0,0,0]},"s":{"k":[100,100,100]}},"ao":0,"shapes":[{"ind":0,"ty":"sh","ks":{"k":{"i":[[0,0],[0,0],[0,0],[0,0]],"o":[[0,0],[0,0],[0,0],[0,0]],"v":[[-300,-54],[300,-54],[300,54],[-300,54]],"c":true}},"nm":"路径 1","mn":"ADBE Vector Shape - Group"},{"ty":"fl","fillEnabled":true,"c":{"k":[1,1,1,1]},"o":{"k":100},"nm":"填充 1","mn":"ADBE Vector Graphic - Fill"}],"ip":0,"op":150,"st":0,"bm":0,"sr":1},{"ddd":0,"ind":8,"ty":0,"nm":"焕彩桌面","refId":"comp_2","ks":{"o":{"k":100},"r":{"k":0},"p":{"k":[{"i":{"x":0.125,"y":1},"o":{"x":0.167,"y":0.167},"n":"0p125_1_0p167_0p167","t":11,"s":[450,666,0],"e":[450,410,0],"to":[0,-42.6666679382324,0],"ti":[0,42.6666679382324,0]},{"t":35}]},"a":{"k":[300,54,0]},"s":{"k":[100,100,100]}},"ao":0,"w":600,"h":108,"ip":0,"op":150,"st":0,"bm":0,"sr":1}]},{"id":"comp_2","layers":[{"ddd":0,"ind":0,"ty":2,"nm":"已关闭.png","cl":"png","refId":"image_3","ks":{"o":{"k":100},"r":{"k":0},"p":{"k":[300,54,0]},"a":{"k":[266.5,18.5,0]},"s":{"k":[100,100,100]}},"ao":0,"ip":0,"op":150,"st":0,"bm":0,"sr":1},{"ddd":0,"ind":2,"ty":4,"nm":"形状图层 2","ks":{"o":{"k":100},"r":{"k":0},"p":{"k":[300,53.75,0]},"a":{"k":[0,0,0]},"s":{"k":[100,100,100]}},"ao":0,"shapes":[{"ind":0,"ty":"sh","ks":{"k":{"i":[[0,0],[0,0],[0,0],[0,0]],"o":[[0,0],[0,0],[0,0],[0,0]],"v":[[-300,-54],[300,-54],[300,54],[-300,54]],"c":true}},"nm":"路径 1","mn":"ADBE Vector Shape - Group"},{"ty":"fl","fillEnabled":true,"c":{"k":[1,1,1,1]},"o":{"k":100},"nm":"填充 1","mn":"ADBE Vector Graphic - Fill"}],"ip":0,"op":150,"st":0,"bm":0,"sr":1}]}],"layers":[{"ddd":0,"ind":0,"ty":4,"nm":"手势","ks":{"o":{"k":[{"i":{"x":[0.833],"y":[0.833]},"o":{"x":[0.167],"y":[0.167]},"n":["0p833_0p833_0p167_0p167"],"t":0,"s":[0],"e":[100]},{"i":{"x":[0.833],"y":[0.833]},"o":{"x":[0.167],"y":[0.167]},"n":["0p833_0p833_0p167_0p167"],"t":3,"s":[100],"e":[100]},{"i":{"x":[0.833],"y":[0.833]},"o":{"x":[0.167],"y":[0.167]},"n":["0p833_0p833_0p167_0p167"],"t":10,"s":[100],"e":[0]},{"i":{"x":[0.833],"y":[0.833]},"o":{"x":[0.167],"y":[0.167]},"n":["0p833_0p833_0p167_0p167"],"t":15,"s":[0],"e":[0]},{"i":{"x":[0.833],"y":[0.833]},"o":{"x":[0.167],"y":[0.167]},"n":["0p833_0p833_0p167_0p167"],"t":31,"s":[0],"e":[100]},{"i":{"x":[0.833],"y":[0.833]},"o":{"x":[0.167],"y":[0.167]},"n":["0p833_0p833_0p167_0p167"],"t":34,"s":[100],"e":[100]},{"i":{"x":[0.833],"y":[0.833]},"o":{"x":[0.167],"y":[0.167]},"n":["0p833_0p833_0p167_0p167"],"t":38,"s":[100],"e":[0]},{"t":41}]},"r":{"k":0},"p":{"k":[{"i":{"x":0.125,"y":1},"o":{"x":0.167,"y":0.167},"n":"0p125_1_0p167_0p167","t":10,"s":[430,490.5,0],"e":[430,400.5,0],"to":[0,-15,0],"ti":[0,7.66666650772095,0]},{"i":{"x":0.833,"y":0.833},"o":{"x":0.167,"y":0.167},"n":"0p833_0p833_0p167_0p167","t":18,"s":[430,400.5,0],"e":[430,444.5,0],"to":[0,-7.66666650772095,0],"ti":[0,-7.33333349227905,0]},{"t":31}]},"a":{"k":[172,-125.5,0]},"s":{"k":[{"i":{"x":[0.187,0.187,0.667],"y":[1,1,0.667]},"o":{"x":[0.167,0.167,0.167],"y":[0.167,0.167,0.167]},"n":["0p187_1_0p167_0p167","0p187_1_0p167_0p167","0p667_0p667_0p167_0p167"],"t":0,"s":[120,120,100],"e":[100,100,100]},{"i":{"x":[0.833,0.833,0.833],"y":[0.833,0.833,0.833]},"o":{"x":[0.167,0.167,0.167],"y":[0.167,0.167,0.167]},"n":["0p833_0p833_0p167_0p167","0p833_0p833_0p167_0p167","0p833_0p833_0p167_0p167"],"t":5,"s":[100,100,100],"e":[105,105,100]},{"i":{"x":[0.667,0.667,0.667],"y":[1,1,0.667]},"o":{"x":[0.167,0.167,0.167],"y":[0.167,0.167,0.167]},"n":["0p667_1_0p167_0p167","0p667_1_0p167_0p167","0p667_0p667_0p167_0p167"],"t":8,"s":[105,105,100],"e":[115,115,100]},{"i":{"x":[0.327,0.327,0.667],"y":[1,1,0.667]},"o":{"x":[0.167,0.167,0.167],"y":[0.167,0.167,0.167]},"n":["0p327_1_0p167_0p167","0p327_1_0p167_0p167","0p667_0p667_0p167_0p167"],"t":31,"s":[115,115,100],"e":[90,90,100]},{"i":{"x":[0.833,0.833,0.833],"y":[0.833,0.833,0.833]},"o":{"x":[0.167,0.167,0.167],"y":[0.167,0.167,0.167]},"n":["0p833_0p833_0p167_0p167","0p833_0p833_0p167_0p167","0p833_0p833_0p167_0p167"],"t":36,"s":[90,90,100],"e":[95,95,100]},{"t":39}]}},"ao":0,"shapes":[{"ty":"gr","it":[{"d":1,"ty":"el","s":{"k":[79.57,79.57]},"p":{"k":[0,0]},"nm":"椭圆路径 1","mn":"ADBE Vector Shape - Ellipse"},{"ty":"fl","fillEnabled":true,"c":{"k":[0.72,0.81,1,1]},"o":{"k":100},"nm":"填充 1","mn":"ADBE Vector Graphic - Fill"},{"ty":"tr","p":{"k":[171.785,-126.215],"ix":2},"a":{"k":[0,0],"ix":1},"s":{"k":[100,100],"ix":3},"r":{"k":0,"ix":6},"o":{"k":100,"ix":7},"sk":{"k":0,"ix":4},"sa":{"k":0,"ix":5},"nm":"变换"}],"nm":"椭圆 1","np":3,"mn":"ADBE Vector Group"}],"ip":0,"op":150,"st":0,"bm":0,"sr":1},{"ddd":0,"ind":1,"ty":4,"nm":"形状图层 2","ks":{"o":{"k":[{"i":{"x":[0.833],"y":[0.833]},"o":{"x":[0.167],"y":[0.167]},"n":["0p833_0p833_0p167_0p167"],"t":31,"s":[0],"e":[30]},{"i":{"x":[0.833],"y":[0.833]},"o":{"x":[0.167],"y":[0.167]},"n":["0p833_0p833_0p167_0p167"],"t":38,"s":[30],"e":[0]},{"t":45}]},"r":{"k":0},"p":{"k":[430,446,0]},"a":{"k":[2,-88,0]},"s":{"k":[{"i":{"x":[0,0.667,0.667],"y":[1,0.667,0.667]},"o":{"x":[0.167,0.167,0.167],"y":[0.167,0.167,0.167]},"n":["0_1_0p167_0p167","0p667_0p667_0p167_0p167","0p667_0p667_0p167_0p167"],"t":31,"s":[100,100,100],"e":[631.284,100,100]},{"t":43}]}},"ao":0,"shapes":[{"ty":"gr","it":[{"ty":"rc","d":1,"s":{"k":[94.787,108]},"p":{"k":[0,0]},"r":{"k":0},"nm":"矩形路径 1","mn":"ADBE Vector Shape - Rect"},{"ty":"fl","fillEnabled":true,"c":{"k":[0.8,0.81,0.81,1]},"o":{"k":100},"nm":"填充 1","mn":"ADBE Vector Graphic - Fill"},{"ty":"tr","p":{"k":[2.008,-90.656],"ix":2},"a":{"k":[0,0],"ix":1},"s":{"k":[100,100],"ix":3},"r":{"k":0,"ix":6},"o":{"k":100,"ix":7},"sk":{"k":0,"ix":4},"sa":{"k":0,"ix":5},"nm":"变换"}],"nm":"矩形 1","np":3,"mn":"ADBE Vector Group"}],"ip":0,"op":150,"st":0,"bm":0,"sr":1},{"ddd":0,"ind":2,"ty":4,"nm":"形状图层 1","ks":{"o":{"k":100},"r":{"k":0},"p":{"k":[430,534,0]},"a":{"k":[0,0,0]},"s":{"k":[100,100,100]}},"ao":0,"shapes":[],"ip":0,"op":150,"st":0,"bm":0,"sr":1},{"ddd":0,"ind":3,"ty":4,"nm":"屏幕 3","td":1,"ks":{"o":{"k":100},"r":{"k":0},"p":{"k":[430,405,0]},"a":{"k":[0,0,0]},"s":{"k":[100,100,100]}},"ao":0,"shapes":[{"ind":0,"ty":"sh","ks":{"k":{"i":[[-3.314,0],[0,0],[0,-3.314],[0,0],[0,0],[0,0]],"o":[[0,0],[3.314,0],[0,0],[0,0],[0,0],[0,-3.314]],"v":[[-286,-175],[286,-175],[292,-169],[292,175],[-292,175],[-292,-169]],"c":true}},"nm":"路径 1","mn":"ADBE Vector Shape - Group"},{"ty":"fl","fillEnabled":true,"c":{"k":[0.95,0.95,0.95,1]},"o":{"k":100},"nm":"填充 1","mn":"ADBE Vector Graphic - Fill"}],"ip":0,"op":150,"st":0,"bm":0,"sr":1},{"ddd":0,"ind":4,"ty":0,"nm":"演示 2","tt":1,"refId":"comp_0","ks":{"o":{"k":[{"i":{"x":[0.833],"y":[0.833]},"o":{"x":[0.167],"y":[0.167]},"n":["0p833_0p833_0p167_0p167"],"t":42,"s":[0],"e":[100]},{"i":{"x":[0.833],"y":[0.833]},"o":{"x":[0.167],"y":[0.167]},"n":["0p833_0p833_0p167_0p167"],"t":49,"s":[100],"e":[100]},{"i":{"x":[0.833],"y":[0.833]},"o":{"x":[0.167],"y":[0.167]},"n":["0p833_0p833_0p167_0p167"],"t":109,"s":[100],"e":[0]},{"t":114}]},"r":{"k":0},"p":{"k":[{"i":{"x":0,"y":1},"o":{"x":0.167,"y":0.167},"n":"0_1_0p167_0p167","t":42,"s":[430,827,0],"e":[430,534,0],"to":[0,-48.8333320617676,0],"ti":[0,48.8333320617676,0]},{"t":65}]},"a":{"k":[540,960,0]},"s":{"k":[100,100,100]}},"ao":0,"w":1080,"h":1920,"ip":0,"op":150,"st":0,"bm":0,"sr":1},{"ddd":0,"ind":5,"ty":2,"nm":"服务.png","cl":"png","refId":"image_2","ks":{"o":{"k":100},"r":{"k":0},"p":{"k":[195.5,269.5,0]},"a":{"k":[29.5,14.5,0]},"s":{"k":[100,100,100]}},"ao":0,"ip":0,"op":150,"st":0,"bm":0,"sr":1},{"ddd":0,"ind":6,"ty":4,"nm":"屏幕 4","td":1,"ks":{"o":{"k":100},"r":{"k":0},"p":{"k":[430,405,0]},"a":{"k":[0,0,0]},"s":{"k":[100,100,100]}},"ao":0,"shapes":[{"ind":0,"ty":"sh","ks":{"k":{"i":[[-3.314,0],[0,0],[0,-3.314],[0,0],[0,0],[0,0]],"o":[[0,0],[3.314,0],[0,0],[0,0],[0,0],[0,-3.314]],"v":[[-286,-98],[286,-98],[292,-92],[292,175],[-292,175],[-292,-92]],"c":true}},"nm":"路径 1","mn":"ADBE Vector Shape - Group"},{"ty":"fl","fillEnabled":true,"c":{"k":[0.95,0.95,0.95,1]},"o":{"k":100},"nm":"填充 1","mn":"ADBE Vector Graphic - Fill"}],"ip":109,"op":259,"st":109,"bm":0,"sr":1},{"ddd":0,"ind":7,"ty":0,"nm":"演示","tt":1,"refId":"comp_1","ks":{"o":{"k":100},"r":{"k":0},"p":{"k":[430,534,0]},"a":{"k":[450,500,0]},"s":{"k":[100,100,100]}},"ao":0,"w":900,"h":1000,"ip":109,"op":259,"st":109,"bm":0,"sr":1},{"ddd":0,"ind":8,"ty":4,"nm":"屏幕","td":1,"ks":{"o":{"k":100},"r":{"k":0},"p":{"k":[430,405,0]},"a":{"k":[0,0,0]},"s":{"k":[100,100,100]}},"ao":0,"shapes":[{"ind":0,"ty":"sh","ks":{"k":{"i":[[-3.314,0],[0,0],[0,-3.314],[0,0],[0,0],[0,0]],"o":[[0,0],[3.314,0],[0,0],[0,0],[0,0],[0,-3.314]],"v":[[-286,-98],[286,-98],[292,-92],[292,175],[-292,175],[-292,-92]],"c":true}},"nm":"路径 1","mn":"ADBE Vector Shape - Group"},{"ty":"fl","fillEnabled":true,"c":{"k":[0.95,0.95,0.95,1]},"o":{"k":100},"nm":"填充 1","mn":"ADBE Vector Graphic - Fill"}],"ip":0,"op":150,"st":0,"bm":0,"sr":1},{"ddd":0,"ind":9,"ty":0,"nm":"演示","tt":1,"refId":"comp_1","ks":{"o":{"k":100},"r":{"k":0},"p":{"k":[430,534,0]},"a":{"k":[450,500,0]},"s":{"k":[100,100,100]}},"ao":0,"w":900,"h":1000,"ip":0,"op":150,"st":0,"bm":0,"sr":1},{"ddd":0,"ind":10,"ty":4,"nm":"屏幕 2","ks":{"o":{"k":100},"r":{"k":0},"p":{"k":[430,405,0]},"a":{"k":[0,0,0]},"s":{"k":[100,100,100]}},"ao":0,"shapes":[{"ind":0,"ty":"sh","ks":{"k":{"i":[[-3.314,0],[0,0],[0,-3.314],[0,0],[0,0],[0,0]],"o":[[0,0],[3.314,0],[0,0],[0,0],[0,0],[0,-3.314]],"v":[[-286,-175],[286,-175],[292,-169],[292,175],[-292,175],[-292,-169]],"c":true}},"nm":"路径 1","mn":"ADBE Vector Shape - Group"},{"ty":"fl","fillEnabled":true,"c":{"k":[0.97,0.97,0.97,1]},"o":{"k":100},"nm":"填充 1","mn":"ADBE Vector Graphic - Fill"}],"ip":0,"op":150,"st":0,"bm":0,"sr":1},{"ddd":0,"ind":11,"ty":4,"nm":"形状图层 5","ks":{"o":{"k":100},"r":{"k":0},"p":{"k":[387,177.5,0]},"a":{"k":[0,0,0]},"s":{"k":[100,100,100]}},"ao":0,"shapes":[{"ind":0,"ty":"sh","ks":{"k":{"i":[[-4.574,0],[0,-4.573],[4.574,0],[0,4.573]],"o":[[4.574,0],[0,4.573],[-4.574,0],[0,-4.573]],"v":[[0,-8.281],[8.282,0],[0,8.281],[-8.282,0]],"c":true}},"nm":"路径 1","mn":"ADBE Vector Shape - Group"},{"ty":"fl","fillEnabled":true,"c":{"k":[0.79,0.85,0.95,1]},"o":{"k":100},"nm":"填充 1","mn":"ADBE Vector Graphic - Fill"}],"ip":0,"op":150,"st":0,"bm":0,"sr":1},{"ddd":0,"ind":12,"ty":4,"nm":"形状图层 4","ks":{"o":{"k":100},"r":{"k":0},"p":{"k":[443.375,176.875,0]},"a":{"k":[0,0,0]},"s":{"k":[100,100,100]}},"ao":0,"shapes":[{"ind":0,"ty":"sh","ks":{"k":{"i":[[-4.319,0],[0,0],[0,-4.319],[4.32,0],[0,0],[0,4.32]],"o":[[0,0],[4.32,0],[0,4.32],[0,0],[-4.319,0],[0,-4.319]],"v":[[-28.987,-7.821],[28.986,-7.821],[36.808,0],[28.986,7.821],[-28.987,7.821],[-36.808,0]],"c":true}},"nm":"路径 1","mn":"ADBE Vector Shape - Group"},{"ty":"fl","fillEnabled":true,"c":{"k":[0.79,0.85,0.95,1]},"o":{"k":100},"nm":"填充 1","mn":"ADBE Vector Graphic - Fill"}],"ip":0,"op":150,"st":0,"bm":0,"sr":1},{"ddd":0,"ind":13,"ty":4,"nm":"形状图层 3","ks":{"o":{"k":100},"r":{"k":0},"p":{"k":[430,349,0]},"a":{"k":[0,0,0]},"s":{"k":[100,100,100]}},"ao":0,"shapes":[{"ind":0,"ty":"sh","ks":{"k":{"i":[[-30.928,0],[0,0],[0,-30.928],[0,0],[0,0],[0,0]],"o":[[0,0],[30.928,0],[0,0],[0,0],[0,0],[0,-30.928]],"v":[[-259.748,-230.952],[259.748,-230.952],[315.748,-174.952],[315.748,230.952],[-315.748,230.952],[-315.748,-174.952]],"c":true}},"nm":"路径 1","mn":"ADBE Vector Shape - Group"},{"ty":"fl","fillEnabled":true,"c":{"k":[0.86,0.9,0.98,1]},"o":{"k":100},"nm":"填充 1","mn":"ADBE Vector Graphic - Fill"}],"ip":0,"op":150,"st":0,"bm":0,"sr":1}],"v":"4.5.3","ddd":0,"ip":0,"op":116,"fr":25,"w":860,"h":580}